minnet/__init__.py
minnet/minnet.py
minnet-1.0.0.dist-info/METADATA
minnet-1.0.0.dist-info/WHEEL
minnet-1.0.0.dist-info/top_level.txt
minnet-1.0.0.dist-info/RECORD
