Metadata-Version: 2.4
Name: minnet
Version: 1.0.0
Summary: Minimalist, text-only Internet client/server in Python.
Author: Gamer0ppgaming
Author-email: gamer07340@gmail.com
License: MIT
Classifier: Programming Language :: Python :: 3
Classifier: License :: OSI Approved :: MIT License
Classifier: Operating System :: OS Independent
Requires-Python: >=3.8
